Sqlite3Helper/__init__.py
Sqlite3Helper/_column.py
Sqlite3Helper/_crypto.py
Sqlite3Helper/_types_def.py
Sqlite3Helper/_util_func.py
Sqlite3Helper/_where.py
Sqlite3Helper/_worker.py
Sqlite3Helper-2.3.0.dist-info/LICENSE
Sqlite3Helper-2.3.0.dist-info/METADATA
Sqlite3Helper-2.3.0.dist-info/WHEEL
Sqlite3Helper-2.3.0.dist-info/top_level.txt
Sqlite3Helper-2.3.0.dist-info/RECORD
