Metadata-Version: 2.1
Name: Sqlite3Helper
Version: 2.3.0
Summary: 一个不安全的 sqlite3 包装库
Author-email: Julian Freeman <freemanjulian372@gmail.com>
Project-URL: Homepage, https://github.com/JulianFreeman/Sqlite3Helper
Project-URL: Repository, https://github.com/JulianFreeman/Sqlite3Helper.git
Project-URL: Changelog, https://github.com/JulianFreeman/Sqlite3Helper/blob/main/CHANGELOG.md
Classifier: License :: OSI Approved :: GNU General Public License v3 (GPLv3)
Classifier: Operating System :: OS Independent
Classifier: Programming Language :: Python :: 3
Requires-Python: >=3.10
License-File: LICENSE
Provides-Extra: crypto
Requires-Dist: cryptography ; extra == 'crypto'
